{
    "id": "jsai2025/247",
    "author": "(jwu)",
    "reviewers": "(jwu)",
    "elements": 10,
    "characters": 267,
    "tags": [
        "counting"
    ],
    "deprecated": false,
    "ja": {
        "question": "ノードの数として正しいものはどれですか？",
        "choice": [
            "4",
            "7",
            "10",
            "6"
        ],
        "answer": "D"
    },
    "en": {
        "question": "Which is the correct number of nodes?",
        "choice": [
            "4",
            "7",
            "10",
            "6"
        ],
        "answer": "D"
    },
    "ko": {
        "question": "노드의 올바른 개수는 다음 중 어느 것인가?",
        "choice": [
            "4",
            "7",
            "10",
            "6"
        ],
        "answer": "D"
    }
}